[
  {
    "code": "1009",
    "group": "1",
    "professor": "LAZARO MORALES ACOSTA",
    "schedules": [
      {
        "time": "11:00-13:00",
        "days": [
          3,
          5
        ],
        "classroom": "15"
      }
    ],
    "professor_id": 59794,
    "first_name": "Lazaro",
    "last_name": "Morales Acosta",
    "rating": 8.3529,
    "num_ratings": 17
  },
  {
    "code": "1009",
    "group": "2",
    "professor": "AXEL YAEL PINO PEREZ",
    "schedules": [
      {
        "time": "19:00-21:00",
        "days": [
          3,
          5
        ],
        "classroom": "15"
      }
    ]
  }
]