[
  {
    "code": "1067",
    "group": "1",
    "professor": "GILBERTO SILVA ROMO",
    "schedules": [
      {
        "time": "10:00-12:00",
        "days": [
          2,
          4
        ],
        "classroom": "27"
      }
    ],
    "professor_id": 78441,
    "first_name": "Gilberto",
    "last_name": "Silva Romo",
    "rating": 7.8421,
    "num_ratings": 19
  },
  {
    "code": "1067",
    "group": "2",
    "professor": "JOSE LUIS ARCOS HERNANDEZ",
    "schedules": [
      {
        "time": "16:00-18:00",
        "days": [
          2,
          4
        ],
        "classroom": "27"
      }
    ],
    "professor_id": 23452,
    "first_name": "José Luis",
    "last_name": "Arcos Hernández",
    "rating": 7.45,
    "num_ratings": 40
  },
  {
    "code": "1067",
    "group": "3",
    "professor": "FERNANDO ROSIQUE NARANJO",
    "schedules": [
      {
        "time": "15:00-17:00",
        "days": [
          2,
          4
        ],
        "classroom": "27"
      }
    ],
    "professor_id": 89992,
    "first_name": "Fernando",
    "last_name": "Rosique Naranjo",
    "rating": 6.25,
    "num_ratings": 8
  },
  {
    "code": "1067",
    "group": "4",
    "professor": "FERNANDO ROSIQUE NARANJO",
    "schedules": [
      {
        "time": "17:00-19:00",
        "days": [
          2,
          4
        ],
        "classroom": "27"
      }
    ],
    "professor_id": 89992,
    "first_name": "Fernando",
    "last_name": "Rosique Naranjo",
    "rating": 6.25,
    "num_ratings": 8
  },
  {
    "code": "1067",
    "group": "5",
    "professor": "YOALLI BIANII HERNANDEZ MARMOLEJO",
    "schedules": [
      {
        "time": "14:00-16:00",
        "days": [
          1,
          3
        ],
        "classroom": "27"
      }
    ],
    "professor_id": 84894,
    "first_name": "Yoalli Bianii",
    "last_name": "Hernández Marmolejo",
    "rating": 5.4167,
    "num_ratings": 36
  }
]